[{"image":"","difficulty":"medium","_id":"682e9d62d715cc08c3f01e1d","question":"EPR is a","choices":[{"_id":"685ac2661e3e48494df1aa30","isCorrect":false,"choice":"Ratio between ambient pressure and exhaust pressure."},{"_id":"685ac2661e3e48494df1aa31","isCorrect":false,"choice":"Ratio between ambient pressure and fan pressure."},{"_id":"685ac2661e3e48494df1aa32","isCorrect":false,"choice":"Ratio between intake pressure and compressor delivery pressure."},{"_id":"685ac2661e3e48494df1aa33","isCorrect":true,"choice":"Ratio between exhaust pressure and intake pressure."}],"explanation":null,"subject":"Technical","book":"Pilot Shala Practice Set","topic":"Engines Thrust"},{"image":"","difficulty":"medium","_id":"682e9d62d715cc08c3f01e1e","question":"In a high by pass engine whose fan max rpm is 20000rpm, when turning at 5000rpm will develop approx.","choices":[{"_id":"685ac2661e3e48494df1aa34","isCorrect":false,"choice":"25% take off thrust."},{"_id":"685ac2661e3e48494df1aa35","isCorrect":false,"choice":"50% take off thrust"},{"_id":"685ac2661e3e48494df1aa36","isCorrect":true,"choice":"5% take off thrust"},{"_id":"685ac2661e3e48494df1aa37","isCorrect":false,"choice":"15% take off thrust."}],"explanation":null,"subject":"Technical","book":"Pilot Shala Practice Set","topic":"Engines Thrust"},{"image":"","difficulty":"medium","_id":"682e9d62d715cc08c3f01e1f","question":"With an increase in altitude which of the following statements are correct for a jet aircraft with constant engine speed for a fixed throttle setting? 1. Temperature and pressure reduce with a resulting drop in thrust. 2. Fuel consumption will increase. 3. Fuel consumption will decrease. 4. Specific fuel consumption will increase. 5. Specific fuel consumption will decrease. 6. Specific fuel consumption stays relatively the same 7. Temperature and pressure will reduce, resulting in an increase in thrust.","choices":[{"_id":"685ac2661e3e48494df1aa38","isCorrect":true,"choice":"1, 3, 6."},{"_id":"685ac2661e3e48494df1aa39","isCorrect":false,"choice":"2, 4, 1."},{"_id":"685ac2661e3e48494df1aa3a","isCorrect":false,"choice":"7, 2, 4."},{"_id":"685ac2661e3e48494df1aa3b","isCorrect":false,"choice":"1, 2, 5"}],"explanation":null,"subject":"Technical","book":"Pilot Shala Practice Set","topic":"Engines Thrust"},{"image":"","difficulty":"medium","_id":"682e9d62d715cc08c3f01e20","question":"The maximum thrust that a jet engine can develop will be:","choices":[{"_id":"685ac2661e3e48494df1aa3c","isCorrect":false,"choice":"Take off thrust."},{"_id":"685ac2661e3e48494df1aa3d","isCorrect":false,"choice":"Go around thrust."},{"_id":"685ac2661e3e48494df1aa3e","isCorrect":false,"choice":"Max climb thrust."},{"_id":"685ac2661e3e48494df1aa3f","isCorrect":true,"choice":"Max Static Thrust."}],"explanation":null,"subject":"Technical","book":"Pilot Shala Practice Set","topic":"Engines Thrust"},{"image":"","difficulty":"medium","_id":"682e9d62d715cc08c3f01e21","question":"As temperature ___________air density ____________ and the mass of air for given engine speed __________ therefore thrust ___________. To maintain the compressor speed however _______ fuel must be added or the compressor will _________.","choices":[{"_id":"685ac2661e3e48494df1aa40","isCorrect":false,"choice":"decreases decreases increases increases less slow down"},{"_id":"685ac2661e3e48494df1aa41","isCorrect":false,"choice":"increases decreases decreases increases more slow down"},{"_id":"685ac2661e3e48494df1aa42","isCorrect":true,"choice":"decreases increases increases increases more slow down"},{"_id":"685ac2661e3e48494df1aa43","isCorrect":false,"choice":"increases decreases increases decreases less speed up"}],"explanation":null,"subject":"Technical","book":"Pilot Shala Practice Set","topic":"Engines Thrust"},{"image":"","difficulty":"medium","_id":"682e9d62d715cc08c3f01e22","question":"From a standing start with an increase in forward speed jet thrust will:","choices":[{"_id":"685ac2661e3e48494df1aa44","isCorrect":false,"choice":"Increase."},{"_id":"685ac2661e3e48494df1aa45","isCorrect":false,"choice":"Stay the same."},{"_id":"685ac2661e3e48494df1aa46","isCorrect":false,"choice":"Decrease."},{"_id":"685ac2661e3e48494df1aa47","isCorrect":true,"choice":"Decrease then recover but will never achieve its initial setting."}],"explanation":null,"subject":"Technical","book":"Pilot Shala Practice Set","topic":"Engines Thrust"},{"image":"","difficulty":"medium","_id":"682e9d62d715cc08c3f01e23","question":"On a turboprop aircraft with a 14 stage axial flow compressor while climbing it will experience:","choices":[{"_id":"685ac2661e3e48494df1aa48","isCorrect":false,"choice":"Increase shaft horse-power increase jet thrust increase fuel consumption"},{"_id":"685ac2661e3e48494df1aa49","isCorrect":true,"choice":"Decrease shaft horse-power decrease jet thrust decrease fuel consumption"},{"_id":"685ac2661e3e48494df1aa4a","isCorrect":false,"choice":"Decrease shaft horse-power increase jet thrust decrease fuel consumption"},{"_id":"685ac2661e3e48494df1aa4b","isCorrect":false,"choice":"Decrease shaft horse-power decrease jet thrust increase fuel consumption"}],"explanation":null,"subject":"Technical","book":"Pilot Shala Practice Set","topic":"Engines Thrust"},{"image":"","difficulty":"medium","_id":"682e9d62d715cc08c3f01e24","question":"On a turboprop aircraft with a 14 stage axial flow compressor while increasing forward speed, it will experience:","choices":[{"_id":"685ac2661e3e48494df1aa4c","isCorrect":false,"choice":"Increase shaft horse-power increase jet thrust"},{"_id":"685ac2661e3e48494df1aa4d","isCorrect":false,"choice":"Decrease shaft horse-power decrease jet thrust"},{"_id":"685ac2661e3e48494df1aa4e","isCorrect":false,"choice":"Decrease shaft horse-power increase jet thrust"},{"_id":"685ac2661e3e48494df1aa4f","isCorrect":true,"choice":"Increase shaft horse-power decrease jet thrust"}],"explanation":null,"subject":"Technical","book":"Pilot Shala Practice Set","topic":"Engines Thrust"},{"image":"","difficulty":"medium","_id":"682e9d62d715cc08c3f01e25","question":"On a part throttled engine, take off thrust would be achieved:","choices":[{"_id":"685ac2661e3e48494df1aa50","isCorrect":false,"choice":"Later than normal due to pressure in the compressor being low."},{"_id":"685ac2661e3e48494df1aa51","isCorrect":false,"choice":"Later than normal due to the EPR being low."},{"_id":"685ac2661e3e48494df1aa52","isCorrect":true,"choice":"Earlier than normal."},{"_id":"685ac2661e3e48494df1aa53","isCorrect":false,"choice":"Later than normal due to the EPR being high."}],"explanation":null,"subject":"Technical","book":"Pilot Shala Practice Set","topic":"Engines Thrust"},{"image":"","difficulty":"medium","_id":"682e9d62d715cc08c3f01e26","question":"In a gas turbine engine:","choices":[{"_id":"685ac2661e3e48494df1aa54","isCorrect":false,"choice":"Ram pressure is maximum at the start of the take off run."},{"_id":"685ac2661e3e48494df1aa55","isCorrect":false,"choice":"Ram pressure is unaffected by airspeed."},{"_id":"685ac2661e3e48494df1aa56","isCorrect":false,"choice":"Thrust is unaffected by the aircraft’s forward speed."},{"_id":"685ac2661e3e48494df1aa57","isCorrect":true,"choice":"Thrust is maximum and ram pressure at minimum at the start of the take off run."}],"explanation":null,"subject":"Technical","book":"Pilot Shala Practice Set","topic":"Engines Thrust"}]