[{"difficulty":"medium","_id":"682e9d62d715cc08c3f01ba0","question":"The logic function of the circuit shown is","choices":[{"_id":"685ac2601e3e48494df1a018","isCorrect":false,"choice":"AND"},{"_id":"685ac2601e3e48494df1a019","isCorrect":true,"choice":"OR"},{"_id":"685ac2601e3e48494df1a01a","isCorrect":false,"choice":"NOR"},{"_id":"685ac2601e3e48494df1a01b","isCorrect":false,"choice":"NOT"}],"image":"https://i0.wp.com/eatpl.in/wp-content/uploads/2023/01/WhatsApp-Image-2023-01-11-at-4.47.13-PM-1.jpeg?fit=280%2C228&ssl=1","explanation":null,"subject":"Technical","book":"Pilot Shala Practice Set","topic":"Electric Logic Gates"},{"difficulty":"medium","_id":"682e9d62d715cc08c3f01ba1","question":"The circuit shown here represents","choices":[{"_id":"685ac2601e3e48494df1a01c","isCorrect":true,"choice":"an ‘AND’ gate"},{"_id":"685ac2601e3e48494df1a01d","isCorrect":false,"choice":"A‘NOR’ gate."},{"_id":"685ac2601e3e48494df1a01e","isCorrect":false,"choice":"an ‘OR’ gate."},{"_id":"685ac2601e3e48494df1a01f","isCorrect":false,"choice":"an ‘EXCLUSIVE OR’ gate."}],"image":"https://i0.wp.com/eatpl.in/wp-content/uploads/2023/01/WhatsApp-Image-2023-01-11-at-4.47.13-PM-2.jpeg?fit=394%2C173&ssl=1","explanation":null,"subject":"Technical","book":"Pilot Shala Practice Set","topic":"Electric Logic Gates"},{"difficulty":"medium","_id":"682e9d62d715cc08c3f01ba2","question":"The gate symbols shown are","choices":[{"_id":"685ac2601e3e48494df1a020","isCorrect":true,"choice":"‘AND’ and ‘NAND’"},{"_id":"685ac2601e3e48494df1a021","isCorrect":false,"choice":"‘EXCLUSIVE OR’ and ‘EXCLUSIVE NOR’"},{"_id":"685ac2601e3e48494df1a022","isCorrect":false,"choice":"‘OR’ and ‘NOR’"},{"_id":"685ac2601e3e48494df1a023","isCorrect":false,"choice":"‘OR’ and ‘EXCLUSIVE OR’"}],"image":"https://i0.wp.com/eatpl.in/wp-content/uploads/2023/01/WhatsApp-Image-2023-01-11-at-4.47.18-PM.jpeg?fit=244%2C213&ssl=1","explanation":null,"subject":"Technical","book":"Pilot Shala Practice Set","topic":"Electric Logic Gates"},{"image":"","difficulty":"medium","_id":"682e9d62d715cc08c3f01ba3","question":"A gate which requires that all inputs must be HIGH to obtain an output would be:","choices":[{"_id":"685ac2601e3e48494df1a024","isCorrect":false,"choice":"a ‘NOR’ gate."},{"_id":"685ac2601e3e48494df1a025","isCorrect":false,"choice":"an ‘OR’ gate."},{"_id":"685ac2601e3e48494df1a026","isCorrect":true,"choice":"an ‘AND’ gate."},{"_id":"685ac2601e3e48494df1a027","isCorrect":false,"choice":"a ‘NOT’ gate."}],"explanation":null,"subject":"Technical","book":"Pilot Shala Practice Set","topic":"Electric Logic Gates"},{"difficulty":"medium","_id":"682e9d62d715cc08c3f01ba4","question":"This diagram represents:","choices":[{"_id":"685ac2601e3e48494df1a028","isCorrect":false,"choice":"an inverter."},{"_id":"685ac2601e3e48494df1a029","isCorrect":false,"choice":"an ‘AND’ gate."},{"_id":"685ac2601e3e48494df1a02a","isCorrect":false,"choice":"an ‘EXCLUSIVE NOR’ gate."},{"_id":"685ac2601e3e48494df1a02b","isCorrect":true,"choice":"an ‘OR’ gate."}],"image":"https://i0.wp.com/eatpl.in/wp-content/uploads/2023/01/WhatsApp-Image-2023-01-11-at-4.47.18-PM-1-1.jpeg?fit=357%2C286&ssl=1","explanation":null,"subject":"Technical","book":"Pilot Shala Practice Set","topic":"Electric Logic Gates"},{"difficulty":"medium","_id":"682e9d62d715cc08c3f01ba5","question":"To obtain logic ‘0’ at output ‘Z’ there must be","choices":[{"_id":"685ac2601e3e48494df1a02c","isCorrect":false,"choice":"logic ‘1’ at ‘X’ and logic ‘0’ at ‘Y’."},{"_id":"685ac2601e3e48494df1a02d","isCorrect":false,"choice":"logic ‘0’ at ‘X’ and logic ‘1’ at ‘Y’."},{"_id":"685ac2601e3e48494df1a02e","isCorrect":true,"choice":"logic ‘1’ at ‘X’ and logic ‘1’ at ‘Y’."},{"_id":"685ac2601e3e48494df1a02f","isCorrect":false,"choice":"logic ‘0’ at ‘X’ and logic ‘0’ at ‘Y’."}],"image":"https://i0.wp.com/eatpl.in/wp-content/uploads/2023/01/WhatsApp-Image-2023-01-11-at-4.47.19-PM.jpeg?fit=236%2C184&ssl=1","explanation":null,"subject":"Technical","book":"Pilot Shala Practice Set","topic":"Electric Logic Gates"},{"image":"","difficulty":"medium","_id":"682e9d62d715cc08c3f01ba6","question":"A transistor:","choices":[{"_id":"685ac2601e3e48494df1a030","isCorrect":false,"choice":"can only be used as an amplifier."},{"_id":"685ac2601e3e48494df1a031","isCorrect":false,"choice":"can be used as a demi-conductor to act as an automatic switch or an amplifier."},{"_id":"685ac2601e3e48494df1a032","isCorrect":false,"choice":"is an inverted silicon controlled rectifier."},{"_id":"685ac2601e3e48494df1a033","isCorrect":true,"choice":"can be used as a semi-conductor to act as an automatic switch or an amplifier."}],"explanation":null,"subject":"Technical","book":"Pilot Shala Practice Set","topic":"Electric Logic Gates"},{"image":"","difficulty":"medium","_id":"682e9d62d715cc08c3f01ba7","question":"A gate with only one input and one output:","choices":[{"_id":"685ac2601e3e48494df1a034","isCorrect":false,"choice":"cannot be a ‘double’ gate."},{"_id":"685ac2601e3e48494df1a035","isCorrect":true,"choice":"is a ‘NOT’ gate."},{"_id":"685ac2601e3e48494df1a036","isCorrect":false,"choice":"can only be a ‘semi-gate’."},{"_id":"685ac2601e3e48494df1a037","isCorrect":false,"choice":"cannot be a ‘NOT’ gate."}],"explanation":null,"subject":"Technical","book":"Pilot Shala Practice Set","topic":"Electric Logic Gates"},{"image":"","difficulty":"medium","_id":"682e9d62d715cc08c3f01ba8","question":"The two most commonly used gates are:","choices":[{"_id":"685ac2601e3e48494df1a038","isCorrect":false,"choice":"‘NOT’ and ‘NOR’"},{"_id":"685ac2601e3e48494df1a039","isCorrect":false,"choice":"‘OR’ and ‘EXCLUSIVE AND’"},{"_id":"685ac2601e3e48494df1a03a","isCorrect":true,"choice":"‘AND’ and ‘OR’"},{"_id":"685ac2601e3e48494df1a03b","isCorrect":false,"choice":"‘AND’ and ‘NAND’"}],"explanation":null,"subject":"Technical","book":"Pilot Shala Practice Set","topic":"Electric Logic Gates"},{"image":"","difficulty":"medium","_id":"682e9d62d715cc08c3f01ba9","question":"Truth tables illustrate the relationship between","choices":[{"_id":"685ac2601e3e48494df1a03c","isCorrect":true,"choice":"inputs and outputs."},{"_id":"685ac2601e3e48494df1a03d","isCorrect":false,"choice":"integrated gates for trouble shooting."},{"_id":"685ac2601e3e48494df1a03e","isCorrect":false,"choice":"the sequence of operation of the gates."},{"_id":"685ac2601e3e48494df1a03f","isCorrect":false,"choice":"electronic and electrical circuits."}],"explanation":null,"subject":"Technical","book":"Pilot Shala Practice Set","topic":"Electric Logic Gates"},{"difficulty":"medium","_id":"682e9d62d715cc08c3f01baa","question":"The output expression for this type of gate is:","choices":[{"_id":"685ac2601e3e48494df1a040","isCorrect":false,"choice":"‘AND’"},{"_id":"685ac2601e3e48494df1a041","isCorrect":false,"choice":"‘EXCLUSIVE NOR’"},{"_id":"685ac2601e3e48494df1a042","isCorrect":true,"choice":"‘EXCLUSIVE OR’"},{"_id":"685ac2601e3e48494df1a043","isCorrect":false,"choice":"‘EXCLUSIVE NOT’"}],"image":"https://i0.wp.com/eatpl.in/wp-content/uploads/2023/01/WhatsApp-Image-2023-01-11-at-4.47.19-PM-1-1.jpeg?fit=242%2C196&ssl=1","explanation":null,"subject":"Technical","book":"Pilot Shala Practice Set","topic":"Electric Logic Gates"},{"difficulty":"medium","_id":"682e9d62d715cc08c3f01bab","question":"In order to energise the relay shown in this circuit, the logic state at the inputs must be:","choices":[{"_id":"685ac2601e3e48494df1a044","isCorrect":false,"choice":"logic ‘0’ at points ‘A’ and ‘B’."},{"_id":"685ac2601e3e48494df1a045","isCorrect":false,"choice":"logic ‘0’ at point ‘A’ and logic ‘1’ at point ‘B’."},{"_id":"685ac2601e3e48494df1a046","isCorrect":true,"choice":"logic ‘1’ at points ‘A’ and ‘B’."},{"_id":"685ac2601e3e48494df1a047","isCorrect":false,"choice":"always identical at points ‘A’ and ‘B’."}],"image":"https://i0.wp.com/eatpl.in/wp-content/uploads/2023/01/WhatsApp-Image-2023-01-11-at-4.47.19-PM-2.jpeg?fit=299%2C237&ssl=1","explanation":null,"subject":"Technical","book":"Pilot Shala Practice Set","topic":"Electric Logic Gates"},{"difficulty":"medium","_id":"682e9d62d715cc08c3f01bac","question":"The type of logic gate represented by this diagram is:","choices":[{"_id":"685ac2601e3e48494df1a048","isCorrect":false,"choice":"‘OR’"},{"_id":"685ac2601e3e48494df1a049","isCorrect":false,"choice":"'NAND’"},{"_id":"685ac2601e3e48494df1a04a","isCorrect":false,"choice":"‘AND’"},{"_id":"685ac2601e3e48494df1a04b","isCorrect":true,"choice":"‘NOT’"}],"image":"https://i0.wp.com/eatpl.in/wp-content/uploads/2023/01/WhatsApp-Image-2023-01-11-at-4.47.20-PM.jpeg?fit=334%2C289&ssl=1","explanation":null,"subject":"Technical","book":"Pilot Shala Practice Set","topic":"Electric Logic Gates"}]