[{"image":"","difficulty":"medium","_id":"682e9d5bd715cc08c3f00879","question":"Variation is the angular difference at a place between True North and Magnetic North and expressed in degrees to the East or West of:","choices":[{"_id":"692fba8cbff3ef35cc6ae669","isCorrect":true,"choice":"True North"},{"_id":"692fba8cbff3ef35cc6ae66a","isCorrect":false,"choice":"Magnetic North"},{"_id":"692fba8cbff3ef35cc6ae66b","isCorrect":false,"choice":"Both"}],"explanation":null,"subject":"Navigation","book":"Pilotshala Practice Set","topic":"Compass and Direction"},{"image":"","difficulty":"medium","_id":"682e9d5bd715cc08c3f00877","question":"For flying in a given direction, the pilot needs a:","choices":[{"_id":"692fba8cbff3ef35cc6ae66c","isCorrect":false,"choice":"Compass"},{"_id":"692fba8cbff3ef35cc6ae66d","isCorrect":true,"choice":"Protractor"},{"_id":"692fba8cbff3ef35cc6ae66e","isCorrect":false,"choice":"Manual."}],"explanation":null,"subject":"Navigation","book":"Pilotshala Practice Set","topic":"Compass and Direction"},{"image":"","difficulty":"medium","_id":"682e9d5bd715cc08c3f0087b","question":"Lines joining places of equal variation shown on a map/chart are called","choices":[{"_id":"692fba8cbff3ef35cc6ae66f","isCorrect":true,"choice":"Isogonals"},{"_id":"692fba8cbff3ef35cc6ae670","isCorrect":false,"choice":"Isobars"},{"_id":"692fba8cbff3ef35cc6ae671","isCorrect":false,"choice":"Aclinic lines."}],"explanation":null,"subject":"Navigation","book":"Pilotshala Practice Set","topic":"Compass and Direction"},{"image":"","difficulty":"medium","_id":"682e9d5bd715cc08c3f0087c","question":"A line joining places of zero variation is called","choices":[{"_id":"692fba8cbff3ef35cc6ae672","isCorrect":false,"choice":"an aclinic line"},{"_id":"692fba8cbff3ef35cc6ae673","isCorrect":false,"choice":"an isoclinic line"},{"_id":"692fba8cbff3ef35cc6ae674","isCorrect":true,"choice":"an agonic line."}],"explanation":null,"subject":"Navigation","book":"Pilotshala Practice Set","topic":"Compass and Direction"},{"image":"","difficulty":"medium","_id":"682e9d5bd715cc08c3f0087a","question":"When Variation is East:","choices":[{"_id":"692fba8cbff3ef35cc6ae675","isCorrect":true,"choice":"Magnetic direction is less than true direction"},{"_id":"692fba8cbff3ef35cc6ae676","isCorrect":false,"choice":"Magnetic direction is more than true direction"},{"_id":"692fba8cbff3ef35cc6ae677","isCorrect":false,"choice":"depends upon the hemisphere."}],"explanation":null,"subject":"Navigation","book":"Pilotshala Practice Set","topic":"Compass and Direction"},{"image":"","difficulty":"medium","_id":"682e9d5bd715cc08c3f00878","question":"The true direction to be followed between two points can be obtained if you have a","choices":[{"_id":"692fba8cbff3ef35cc6ae678","isCorrect":true,"choice":"Compass"},{"_id":"692fba8cbff3ef35cc6ae679","isCorrect":false,"choice":"Map"},{"_id":"692fba8cbff3ef35cc6ae67a","isCorrect":false,"choice":"Radio compass."}],"explanation":null,"subject":"Navigation","book":"Pilotshala Practice Set","topic":"Compass and Direction"}]